{
    "type":  "minecraft:crafting_shaped",
    "pattern":  [
                    "lgl",
                    "gdg",
                    "cgc"
                ],
    "key":  {
                "l":  "minecraft:lapis_lazuli",
                "g":  "minecraft:gold_nugget",
                "d":  "dragonsurvival:heart_element",
                "c":  "dragonsurvival:charged_coal"
            },
    "result":  {
                   "id":  "dragonsurvival:weak_dragon_heart",
                   "count":  1
               }
}
